[
  {
    "accountID": "ca1eeeca-231f-4a91-a740-04eaeb043516",
    "accountName": "performance-testing",
    "benefitCost": 12190.55,
    "commitmentGranularity": "Hourly",
    "costWithoutBenefit": 15528.11,
    "coveragePercentage": 92.219,
    "id": "/subscriptions/20a146f0-6ceb-48c4-8d60-f560f3608a61/resourceGroups/rg-test/providers/Microsoft.Compute/virtualMachines/vm-server",
    "lookbackPeriod": "Last 30 Days",
    "name": "ebdcfba4eaafbbd48fe7e35f3bcdd23e74d9daa4edca0e6a5cfc1c15da5e6fb2",
    "overageCost": 1798.25,
    "recommendedQuantity": 20.425,
    "resourceGroup": null,
    "resourceType": "Standard_D16s_v3",
    "savings": 516.639,
    "savingsCurrency": "US$",
    "savingsPercentage": 31.169,
    "scope": "Subscription",
    "service": "Microsoft.Compute",
    "term": "3 Year",
    "totalCost": 11333.49,
    "totalHours": 733,
    "wastageCost": 29.01
  },
  {
    "accountID": "ceee86e2-a6cf-4a62-8004-1313cc581679",
    "accountName": "data-science",
    "benefitCost": 15617.89,
    "commitmentGranularity": "Hourly",
    "costWithoutBenefit": 19811.39,
    "coveragePercentage": 92.899,
    "id": "/subscriptions/5cfcdfaa-ffb7-4474-8ae7-ef003e2a7478/resourceGroups/rg-staging/providers/Microsoft.Compute/virtualMachines/vm-server",
    "lookbackPeriod": "Last 30 Days",
    "name": "e6a3a84e23da0baa45ed65e89f7e38cfeac3f6dc77af94abf4f9ef5f8d36f1b7",
    "overageCost": 1993.91,
    "recommendedQuantity": 22.115,
    "resourceGroup": null,
    "resourceType": "Standard_D4s_v3",
    "savings": 447.612,
    "savingsCurrency": "US$",
    "savingsPercentage": 26.099,
    "scope": "Subscription",
    "service": "Microsoft.Compute",
    "term": "3 Year",
    "totalCost": 12441.53,
    "totalHours": 797,
    "wastageCost": 31.79
  },
  {
    "accountID": "1aec08f2-c15d-4c32-919c-4bab940f69f3",
    "accountName": "mobile-backend",
    "benefitCost": 14521.69,
    "commitmentGranularity": "Hourly",
    "costWithoutBenefit": 17835.47,
    "coveragePercentage": 93.699,
    "id": "/subscriptions/e1d31b88-0b2f-496a-a524-bfa4c9be5ec6/resourceGroups/rg-test/providers/Microsoft.Compute/virtualMachines/vm-server",
    "lookbackPeriod": "Last 30 Days",
    "name": "7a2ea9c3bcbaefaa43f6c21cdd0e77d15eeb8a1d4da93fbf5af8d36a65cfa45d",
    "overageCost": 2014.59,
    "recommendedQuantity": 23.505,
    "resourceGroup": null,
    "resourceType": "Standard_D16s_v4",
    "savings": 800.116,
    "savingsCurrency": "US$",
    "savingsPercentage": 28.699,
    "scope": "Subscription",
    "service": "Microsoft.Compute",
    "term": "3 Year",
    "totalCost": 13011.71,
    "totalHours": 841,
    "wastageCost": 32.93
  },
  {
    "accountID": "13e8d4fc-8226-45a0-88cf-2979d3e9eba9",
    "accountName": "ci-cd-pipeline",
    "benefitCost": 12783.39,
    "commitmentGranularity": "Hourly",
    "costWithoutBenefit": 15295.81,
    "coveragePercentage": 94.399,
    "id": "/subscriptions/301590f2-c879-4eb8-a086-5e969723a337/resourceGroups/rg-dev/providers/Microsoft.Compute/virtualMachines/vm-server",
    "lookbackPeriod": "Last 30 Days",
    "name": "8a4b2f2ce0df6cc8c6b7dc34dd0a3e14ae0ed9d66d7a45c85f41dab8b9a8b5ea",
    "overageCost": 2012.13,
    "recommendedQuantity": 24.905,
    "resourceGroup": null,
    "resourceType": "Standard_D4s_v4",
    "savings": 1021.063,
    "savingsCurrency": "US$",
    "savingsPercentage": 34.499,
    "scope": "Subscription",
    "service": "Microsoft.Compute",
    "term": "3 Year",
    "totalCost": 12533.27,
    "totalHours": 819,
    "wastageCost": 34.19
  },
  {
    "accountID": "1af450b2-ce7a-4af5-9ebc-a13461fe1e32",
    "accountName": "content-management",
    "benefitCost": 13887.51,
    "commitmentGranularity": "Hourly",
    "costWithoutBenefit": 16911.31,
    "coveragePercentage": 93.299,
    "id": "/subscriptions/569feef6-bdbc-40e5-a396-e782345a36e7/resourceGroups/rg-dev/providers/Microsoft.Compute/virtualMachines/vm-server",
    "lookbackPeriod": "Last 30 Days",
    "name": "dfb9b3a0ee5a65b9e4aa6edaf17b45f74dcafaadcd1f34c35da53d23bb44cf15",
    "overageCost": 1923.62,
    "recommendedQuantity": 22.715,
    "resourceGroup": null,
    "resourceType": "Standard_D2s_v5",
    "savings": 356.598,
    "savingsCurrency": "US$",
    "savingsPercentage": 29.799,
    "scope": "Subscription",
    "service": "Microsoft.Compute",
    "term": "3 Year",
    "totalCost": 12911.89,
    "totalHours": 833,
    "wastageCost": 35.79
  },
  {
    "accountID": "6383b3a2-a8c4-4c07-8acf-f38e08fc7622",
    "accountName": "staging-workloads",
    "benefitCost": 14291.49,
    "commitmentGranularity": "Hourly",
    "costWithoutBenefit": 17428.19,
    "coveragePercentage": 93.099,
    "id": "/subscriptions/dd31cacf-3273-4fe8-aad2-816cd99e3c0f/resourceGroups/rg-dev/providers/Microsoft.Compute/virtualMachines/vm-server",
    "lookbackPeriod": "Last 30 Days",
    "name": "9c7e44c0e3a3dd49b5d95a11e48cd5f5ae94daeb76bde4d6af6bece8a14e9a93",
    "overageCost": 2036.43,
    "recommendedQuantity": 24.315,
    "resourceGroup": null,
    "resourceType": "Standard_D2s_v5",
    "savings": 766.812,
    "savingsCurrency": "US$",
    "savingsPercentage": 29.899,
    "scope": "Subscription",
    "service": "Microsoft.Compute",
    "term": "3 Year",
    "totalCost": 13191.81,
    "totalHours": 859,
    "wastageCost": 36.73
  },
  {
    "accountID": "8752afcb-f9b4-453b-b34c-cb9f3a9a0247",
    "accountName": "logging-infrastructure",
    "benefitCost": 15482.51,
    "commitmentGranularity": "Hourly",
    "costWithoutBenefit": 18841.79,
    "coveragePercentage": 92.599,
    "id": "/subscriptions/6d575531-e403-492f-b681-dca04ec22bdf/resourceGroups/rg-staging/providers/Microsoft.Compute/virtualMachines/vm-server",
    "lookbackPeriod": "Last 30 Days",
    "name": "3e44bcf14d35c7e8d15a7f5cde6aaad0daebd1ff8d6f89dc6d4bb5ab94ea2b12",
    "overageCost": 2059.01,
    "recommendedQuantity": 25.815,
    "resourceGroup": null,
    "resourceType": "Standard_D16s_v3",
    "savings": 834.661,
    "savingsCurrency": "US$",
    "savingsPercentage": 28.399,
    "scope": "Subscription",
    "service": "Microsoft.Compute",
    "term": "3 Year",
    "totalCost": 13511.97,
    "totalHours": 891,
    "wastageCost": 37.67
  },
  {
    "accountID": "9c6588cd-ca5e-429d-adc7-5292d3880914",
    "accountName": "marketing-analytics",
    "benefitCost": 16375.31,
    "commitmentGranularity": "Hourly",
    "costWithoutBenefit": 20328.81,
    "coveragePercentage": 93.299,
    "id": "/subscriptions/86479268-dabb-4bd4-bd9a-68a5b26ff12a/resourceGroups/rg-staging/providers/Microsoft.Compute/virtualMachines/vm-server",
    "lookbackPeriod": "Last 30 Days",
    "name": "14db1b44f0ad45de8da55af0efbc35d34ae53d8b3a7dca23ec5cd6e8a4b5b43c",
    "overageCost": 2029.42,
    "recommendedQuantity": 26.415,
    "resourceGroup": null,
    "resourceType": "Standard_D16s_v4",
    "savings": 681.169,
    "savingsCurrency": "US$",
    "savingsPercentage": 27.699,
    "scope": "Subscription",
    "service": "Microsoft.Compute",
    "term": "3 Year",
    "totalCost": 14319.69,
    "totalHours": 923,
    "wastageCost": 39.53
  },
  {
    "accountID": "912102ae-2e57-4094-bb8a-63a7d1c38207",
    "accountName": "finance-reporting",
    "benefitCost": 15987.91,
    "commitmentGranularity": "Hourly",
    "costWithoutBenefit": 19511.39,
    "coveragePercentage": 92.299,
    "id": "/subscriptions/285ca40c-c863-411b-8d90-dc22484362cf/resourceGroups/rg-dev/providers/Microsoft.Compute/virtualMachines/vm-server",
    "lookbackPeriod": "Last 30 Days",
    "name": "5da4bceec3ebdc3cd98b0a1ff2ad35d45a43f1c79b4c2d7e14e8ac15d3ddcc20",
    "overageCost": 2123.31,
    "recommendedQuantity": 27.915,
    "resourceGroup": null,
    "resourceType": "Standard_D16s_v4",
    "savings": 678.867,
    "savingsCurrency": "US$",
    "savingsPercentage": 30.099,
    "scope": "Subscription",
    "service": "Microsoft.Compute",
    "term": "3 Year",
    "totalCost": 14928.01,
    "totalHours": 961,
    "wastageCost": 41.29
  },
  {
    "accountID": "57e25d4f-1ba6-4ac3-8ae9-455e3f0236ec",
    "accountName": "demo-environment",
    "benefitCost": 17159.49,
    "commitmentGranularity": "Hourly",
    "costWithoutBenefit": 21135.11,
    "coveragePercentage": 91.199,
    "id": "/subscriptions/52414b11-cb6f-46a7-aa9b-8d573e3606fa/resourceGroups/rg-test/providers/Microsoft.Compute/virtualMachines/vm-server",
    "lookbackPeriod": "Last 30 Days",
    "name": "8a44dcf5e9c43cd48f5f0ce37aaefc6f8f3b2cfa35b2eebe0d2a7a9ae14b4b23",
    "overageCost": 2176.46,
    "recommendedQuantity": 28.715,
    "resourceGroup": null,
    "resourceType": "Standard_D16s_v3",
    "savings": 214.346,
    "savingsCurrency": "US$",
    "savingsPercentage": 28.899,
    "scope": "Subscription",
    "service": "Microsoft.Compute",
    "term": "3 Year",
    "totalCost": 15244.19,
    "totalHours": 1011,
    "wastageCost": 43.81
  },
  {
    "accountID": "f048a88c-9bc9-43cf-a30d-f48c94708866",
    "accountName": "hr-systems",
    "benefitCost": 18132.69,
    "commitmentGranularity": "Hourly",
    "costWithoutBenefit": 22301.79,
    "coveragePercentage": 91.099,
    "id": "/subscriptions/f6daa794-9ae1-430f-a333-cf865052811d/resourceGroups/rg-staging/providers/Microsoft.Compute/virtualMachines/vm-server",
    "lookbackPeriod": "Last 30 Days",
    "name": "1e44bcf14d35c7e8d15a7f5cde6aaad0daebd1ff8d6f89dc6d4bb5ab94ea2b13",
    "overageCost": 2269.04,
    "recommendedQuantity": 30.315,
    "resourceGroup": null,
    "resourceType": "Standard_D8s_v5",
    "savings": 831.306,
    "savingsCurrency": "US$",
    "savingsPercentage": 28.699,
    "scope": "Subscription",
    "service": "Microsoft.Compute",
    "term": "3 Year",
    "totalCost": 15533.76,
    "totalHours": 1055,
    "wastageCost": 46.69
  },
  {
    "accountID": "ca1eeeca-231f-4a91-a740-04eaeb043516",
    "accountName": "staging-workloads",
    "benefitCost": 19145.31,
    "commitmentGranularity": "Hourly",
    "costWithoutBenefit": 23473.81,
    "coveragePercentage": 91.099,
    "id": "/subscriptions/5386b047-42d1-4bda-826b-c4680c964895/resourceGroups/rg-dev/providers/Microsoft.Compute/virtualMachines/vm-server",
    "lookbackPeriod": "Last 30 Days",
    "name": "14db1b44f0ad45de8da55af0efbc35d34ae53d8b3a7dca23ec5cd6e8a4b5b43d",
    "overageCost": 2324.42,
    "recommendedQuantity": 31.815,
    "resourceGroup": null,
    "resourceType": "Standard_D8s_v5",
    "savings": 958.804,
    "savingsCurrency": "US$",
    "savingsPercentage": 28.599,
    "scope": "Subscription",
    "service": "Microsoft.Compute",
    "term": "3 Year",
    "totalCost": 15854.09,
    "totalHours": 1097,
    "wastageCost": 49.59
  },
  {
    "accountID": "ceee86e2-a6cf-4a62-8004-1313cc581679",
    "accountName": "monitoring-observability",
    "benefitCost": 20258.81,
    "commitmentGranularity": "Hourly",
    "costWithoutBenefit": 24723.81,
    "coveragePercentage": 91.099,
    "id": "/subscriptions/8270d40e-5941-4fa3-bfee-8638f0ce441c/resourceGroups/rg-dev/providers/Microsoft.Compute/virtualMachines/vm-server",
    "lookbackPeriod": "Last 30 Days",
    "name": "3e44bcf14d35c7e8d15a7f5cde6aaad0daebd1ff8d6f89dc6d4bb5ab94ea2b14",
    "overageCost": 2389.01,
    "recommendedQuantity": 33.315,
    "resourceGroup": null,
    "resourceType": "Standard_D4s_v4",
    "savings": 883.925,
    "savingsCurrency": "US$",
    "savingsPercentage": 28.499,
    "scope": "Subscription",
    "service": "Microsoft.Compute",
    "term": "3 Year",
    "totalCost": 16274.88,
    "totalHours": 1141,
    "wastageCost": 53.49
  },
  {
    "accountID": "1aec08f2-c15d-4c32-919c-4bab940f69f3",
    "accountName": "production-platform",
    "benefitCost": 21371.93,
    "commitmentGranularity": "Hourly",
    "costWithoutBenefit": 26153.81,
    "coveragePercentage": 91.099,
    "id": "/subscriptions/f0f964db-aef3-4c94-b8a7-29c870c7bb72/resourceGroups/rg-dev/providers/Microsoft.Compute/virtualMachines/vm-server",
    "lookbackPeriod": "Last 30 Days",
    "name": "5da4bceec3ebdc3cd98b0a1ff2ad35d45a43f1c79b4c2d7e14e8ac15d3ddcc21",
    "overageCost": 2519.01,
    "recommendedQuantity": 34.815,
    "resourceGroup": null,
    "resourceType": "Standard_D8s_v5",
    "savings": 795.432,
    "savingsCurrency": "US$",
    "savingsPercentage": 28.399,
    "scope": "Subscription",
    "service": "Microsoft.Compute",
    "term": "3 Year",
    "totalCost": 16792.97,
    "totalHours": 1187,
    "wastageCost": 57.39
  },
  {
    "accountID": "13e8d4fc-8226-45a0-88cf-2979d3e9eba9",
    "accountName": "mobile-backend",
    "benefitCost": "22584.91",
    "commitmentGranularity": "Hourly",
    "costWithoutBenefit": "27641.81",
    "coveragePercentage": 91.099,
    "id": "/subscriptions/1847e40d-c666-4a4b-85e7-8cc2f65ae80a/resourceGroups/rg-staging/providers/Microsoft.Compute/virtualMachines/vm-server",
    "lookbackPeriod": "Last 30 Days",
    "name": "14db1b44f0ad45de8da55af0efbc35d34ae53d8b3a7dca23ec5cd6e8a4b5b43e",
    "overageCost": "2654.01",
    "recommendedQuantity": "36.315",
    "resourceGroup": null,
    "resourceType": "Standard_D4s_v4",
    "savings": 197.147,
    "savingsCurrency": "US$",
    "savingsPercentage": "28.299",
    "scope": "Subscription",
    "service": "Microsoft.Compute",
    "term": "3 Year",
    "totalCost": "17307.03",
    "totalHours": "1221",
    "wastageCost": "61.29"
  },
  {
    "accountID": "1af450b2-ce7a-4af5-9ebc-a13461fe1e32",
    "accountName": "artifact-storage",
    "benefitCost": "23907.93",
    "commitmentGranularity": "Hourly",
    "costWithoutBenefit": "29223.81",
    "coveragePercentage": "91.099",
    "id": "/subscriptions/993700a2-feb7-4d31-b75d-55fc5b6ed077/resourceGroups/rg-staging/providers/Microsoft.Compute/virtualMachines/vm-server",
    "lookbackPeriod": "Last 30 Days",
    "name": "3e44bcf14d35c7e8d15a7f5cde6aaad0daebd1ff8d6f89dc6d4bb5ab94ea2b15",
    "overageCost": "2819.01",
    "recommendedQuantity": "37.815",
    "resourceGroup": null,
    "resourceType": "Standard_D32s_v3",
    "savings": 730.537,
    "savingsCurrency": "US$",
    "savingsPercentage": "28.199",
    "scope": "Subscription",
    "service": "Microsoft.Compute",
    "term": "3 Year",
    "totalCost": "17608.98",
    "totalHours": "1265",
    "wastageCost": "65.19"
  }
]