[
  {
    "accountID": "marketing-team",
    "accountName": "marketing-team",
    "cpuAverage": 0.21,
    "cpuMaximum": 0.98,
    "cpuMinimum": 0.58,
    "hostname": null,
    "id": "4254929116841923947",
    "newResourceType": "Stop VM Instance",
    "platform": "Intel Cascade Lake",
    "primaryImpactCategory": "COST",
    "priority": "P3",
    "projectNumber": "107654322904",
    "recommendationDetails": "Save cost by stopping Idle VM 'data-scraper-06'.",
    "recommenderSubtype": "STOP_VM",
    "region": "us-central1",
    "resourceID": "4254929116841923947",
    "resourceName": "data-scraper-06",
    "resourceType": "n1-standard-8",
    "savings": 217.35,
    "savingsCurrency": "US$",
    "selfLink": "https://www.googleapis.com/compute/v1/projects/marketing-team/zones/us-central1-a/instances/data-scraper-06",
    "service": "Compute Engine",
    "state": "ACTIVE",
    "status": "RUNNING",
    "tags": "project=app-project-012, env=prod",
    "zone": "us-central1-a"
  },
  {
    "accountID": "devops-team",
    "accountName": "devops-team",
    "cpuAverage": 0.89,
    "cpuMaximum": 0.19,
    "cpuMinimum": 0.65,
    "hostname": null,
    "id": "3181249156841923947",
    "newResourceType": "Stop VM Instance",
    "platform": "Intel Skylake",
    "primaryImpactCategory": "COST",
    "priority": "P1",
    "projectNumber": "982321270904",
    "recommendationDetails": "Save cost by stopping Idle VM 'load-balancer-02'.",
    "recommenderSubtype": "STOP_VM",
    "region": "europe-west4",
    "resourceID": "3181249156841923947",
    "resourceName": "load-balancer-02",
    "resourceType": "n1-standard-2",
    "savings": 63.19,
    "savingsCurrency": "US$",
    "selfLink": "https://www.googleapis.com/compute/v1/projects/devops-team/zones/europe-west4-b/instances/load-balancer-02",
    "service": "Compute Engine",
    "state": "ACTIVE",
    "status": "RUNNING",
    "tags": "project=app-project-015, env=stg",
    "zone": "europe-west4-b"
  },
  {
    "accountID": "sales-team",
    "accountName": "sales-team",
    "cpuAverage": 0.35,
    "cpuMaximum": 0.91,
    "cpuMinimum": 0.71,
    "hostname": null,
    "id": "6719249116841923947",
    "newResourceType": "Stop VM Instance",
    "platform": "Intel Haswell",
    "primaryImpactCategory": "COST",
    "priority": "P2",
    "projectNumber": "645632890904",
    "recommendationDetails": "Save cost by stopping Idle VM 'api-gateway-05'.",
    "recommenderSubtype": "STOP_VM",
    "region": "us-west4",
    "resourceID": "6719249116841923947",
    "resourceName": "api-gateway-05",
    "resourceType": "n1-standard-6",
    "savings": 151.49,
    "savingsCurrency": "US$",
    "selfLink": "https://www.googleapis.com/compute/v1/projects/sales-team/zones/us-west4-a/instances/api-gateway-05",
    "service": "Compute Engine",
    "state": "ACTIVE",
    "status": "RUNNING",
    "tags": "project=app-project-027, env=poc",
    "zone": "us-west4-a"
  },
  {
    "accountID": "finance-team",
    "accountName": "finance-team",
    "cpuAverage": 0.47,
    "cpuMaximum": 0.85,
    "cpuMinimum": 0.29,
    "hostname": null,
    "id": "9156729116841923947",
    "newResourceType": "Stop VM Instance",
    "platform": "Intel Broadwell",
    "primaryImpactCategory": "COST",
    "priority": "P4",
    "projectNumber": "982321270904",
    "recommendationDetails": "Save cost by stopping Idle VM 'scheduler-08'.",
    "recommenderSubtype": "STOP_VM",
    "region": "europe-west1",
    "resourceID": "9156729116841923947",
    "resourceName": "scheduler-08",
    "resourceType": "n1-standard-4",
    "savings": 109.16,
    "savingsCurrency": "US$",
    "selfLink": "https://www.googleapis.com/compute/v1/projects/finance-team/zones/europe-west1-b/instances/scheduler-08",
    "service": "Compute Engine",
    "state": "ACTIVE",
    "status": "RUNNING",
    "tags": "project=app-project-035, env=uat",
    "zone": "europe-west1-b"
  },
  {
    "accountID": "marketing-team",
    "accountName": "marketing-team",
    "cpuAverage": 0.23,
    "cpuMaximum": 0.97,
    "cpuMinimum": 0.59,
    "hostname": null,
    "id": "4254929116841923948",
    "newResourceType": "Stop VM Instance",
    "platform": "Intel Cascade Lake",
    "primaryImpactCategory": "COST",
    "priority": "P3",
    "projectNumber": "107654322904",
    "recommendationDetails": "Save cost by stopping Idle VM 'data-scraper-06'.",
    "recommenderSubtype": "STOP_VM",
    "region": "us-central1",
    "resourceID": "4254929116841923948",
    "resourceName": "data-scraper-06",
    "resourceType": "n1-standard-8",
    "savings": 217.35,
    "savingsCurrency": "US$",
    "selfLink": "https://www.googleapis.com/compute/v1/projects/marketing-team/zones/us-central1-a/instances/data-scraper-06",
    "service": "Compute Engine",
    "state": "ACTIVE",
    "status": "RUNNING",
    "tags": "project=app-project-012, env=prod",
    "zone": "us-central1-a"
  },
  {
    "accountID": "devops-team",
    "accountName": "devops-team",
    "cpuAverage": 0.93,
    "cpuMaximum": 0.17,
    "cpuMinimum": 0.67,
    "hostname": null,
    "id": "3181249156841923948",
    "newResourceType": "Stop VM Instance",
    "platform": "Intel Skylake",
    "primaryImpactCategory": "COST",
    "priority": "P1",
    "projectNumber": "982321270904",
    "recommendationDetails": "Save cost by stopping Idle VM 'load-balancer-02'.",
    "recommenderSubtype": "STOP_VM",
    "region": "europe-west4",
    "resourceID": "3181249156841923948",
    "resourceName": "load-balancer-02",
    "resourceType": "n1-standard-2",
    "savings": 63.19,
    "savingsCurrency": "US$",
    "selfLink": "https://www.googleapis.com/compute/v1/projects/devops-team/zones/europe-west4-b/instances/load-balancer-02",
    "service": "Compute Engine",
    "state": "ACTIVE",
    "status": "RUNNING",
    "tags": "project=app-project-015, env=stg",
    "zone": "europe-west4-b"
  },
  {
    "accountID": "sales-team",
    "accountName": "sales-team",
    "cpuAverage": 0.37,
    "cpuMaximum": 0.93,
    "cpuMinimum": 0.73,
    "hostname": null,
    "id": "6719249116841923948",
    "newResourceType": "Stop VM Instance",
    "platform": "Intel Haswell",
    "primaryImpactCategory": "COST",
    "priority": "P2",
    "projectNumber": "645632890904",
    "recommendationDetails": "Save cost by stopping Idle VM 'api-gateway-05'.",
    "recommenderSubtype": "STOP_VM",
    "region": "us-west4",
    "resourceID": "6719249116841923948",
    "resourceName": "api-gateway-05",
    "resourceType": "n1-standard-6",
    "savings": 151.49,
    "savingsCurrency": "US$",
    "selfLink": "https://www.googleapis.com/compute/v1/projects/sales-team/zones/us-west4-a/instances/api-gateway-05",
    "service": "Compute Engine",
    "state": "ACTIVE",
    "status": "RUNNING",
    "tags": "project=app-project-027, env=poc",
    "zone": "us-west4-a"
  },
  {
    "accountID": "finance-team",
    "accountName": "finance-team",
    "cpuAverage": 0.51,
    "cpuMaximum": 0.83,
    "cpuMinimum": 0.31,
    "hostname": null,
    "id": "9156729116841923948",
    "newResourceType": "Stop VM Instance",
    "platform": "Intel Broadwell",
    "primaryImpactCategory": "COST",
    "priority": "P4",
    "projectNumber": "982321270904",
    "recommendationDetails": "Save cost by stopping Idle VM 'scheduler-08'.",
    "recommenderSubtype": "STOP_VM",
    "region": "europe-west1",
    "resourceID": "9156729116841923948",
    "resourceName": "scheduler-08",
    "resourceType": "n1-standard-4",
    "savings": 109.16,
    "savingsCurrency": "US$",
    "selfLink": "https://www.googleapis.com/compute/v1/projects/finance-team/zones/europe-west1-b/instances/scheduler-08",
    "service": "Compute Engine",
    "state": "ACTIVE",
    "status": "RUNNING",
    "tags": "project=app-project-035, env=uat",
    "zone": "europe-west1-b"
  },
  {
    "accountID": "marketing-team",
    "accountName": "marketing-team",
    "cpuAverage": 0.25,
    "cpuMaximum": 0.99,
    "cpuMinimum": 0.61,
    "hostname": null,
    "id": "4254929116841923949",
    "newResourceType": "Stop VM Instance",
    "platform": "Intel Cascade Lake",
    "primaryImpactCategory": "COST",
    "priority": "P3",
    "projectNumber": "107654322904",
    "recommendationDetails": "Save cost by stopping Idle VM 'data-scraper-06'.",
    "recommenderSubtype": "STOP_VM",
    "region": "us-central1",
    "resourceID": "4254929116841923949",
    "resourceName": "data-scraper-06",
    "resourceType": "n1-standard-8",
    "savings": 217.35,
    "savingsCurrency": "US$",
    "selfLink": "https://www.googleapis.com/compute/v1/projects/marketing-team/zones/us-central1-a/instances/data-scraper-06",
    "service": "Compute Engine",
    "state": "ACTIVE",
    "status": "RUNNING",
    "tags": "project=app-project-012, env=prod",
    "zone": "us-central1-a"
  },
  {
    "accountID": "devops-team",
    "accountName": "devops-team",
    "cpuAverage": 0.95,
    "cpuMaximum": 0.15,
    "cpuMinimum": 0.69,
    "hostname": null,
    "id": "3181249156841923949",
    "newResourceType": "Stop VM Instance",
    "platform": "Intel Skylake",
    "primaryImpactCategory": "COST",
    "priority": "P1",
    "projectNumber": "982321270904",
    "recommendationDetails": "Save cost by stopping Idle VM 'load-balancer-02'.",
    "recommenderSubtype": "STOP_VM",
    "region": "europe-west4",
    "resourceID": "3181249156841923949",
    "resourceName": "load-balancer-02",
    "resourceType": "n1-standard-2",
    "savings": 63.19,
    "savingsCurrency": "US$",
    "selfLink": "https://www.googleapis.com/compute/v1/projects/devops-team/zones/europe-west4-b/instances/load-balancer-02",
    "service": "Compute Engine",
    "state": "ACTIVE",
    "status": "RUNNING",
    "tags": "project=app-project-015, env=stg",
    "zone": "europe-west4-b"
  },
  {
    "accountID": "sales-team",
    "accountName": "sales-team",
    "cpuAverage": 0.39,
    "cpuMaximum": 0.95,
    "cpuMinimum": 0.75,
    "hostname": null,
    "id": "6719249116841923949",
    "newResourceType": "Stop VM Instance",
    "platform": "Intel Haswell",
    "primaryImpactCategory": "COST",
    "priority": "P2",
    "projectNumber": "645632890904",
    "recommendationDetails": "Save cost by stopping Idle VM 'api-gateway-05'.",
    "recommenderSubtype": "STOP_VM",
    "region": "us-west4",
    "resourceID": "6719249116841923949",
    "resourceName": "api-gateway-05",
    "resourceType": "n1-standard-6",
    "savings": 151.49,
    "savingsCurrency": "US$",
    "selfLink": "https://www.googleapis.com/compute/v1/projects/sales-team/zones/us-west4-a/instances/api-gateway-05",
    "service": "Compute Engine",
    "state": "ACTIVE",
    "status": "RUNNING",
    "tags": "project=app-project-027, env=poc",
    "zone": "us-west4-a"
  },
  {
    "accountID": "finance-team",
    "accountName": "finance-team",
    "cpuAverage": 0.53,
    "cpuMaximum": 0.81,
    "cpuMinimum": 0.33,
    "hostname": null,
    "id": "9156729116841923949",
    "newResourceType": "Stop VM Instance",
    "platform": "Intel Broadwell",
    "primaryImpactCategory": "COST",
    "priority": "P4",
    "projectNumber": "982321270904",
    "recommendationDetails": "Save cost by stopping Idle VM 'scheduler-08'.",
    "recommenderSubtype": "STOP_VM",
    "region": "europe-west1",
    "resourceID": "9156729116841923949",
    "resourceName": "scheduler-08",
    "resourceType": "n1-standard-4",
    "savings": 109.16,
    "savingsCurrency": "US$",
    "selfLink": "https://www.googleapis.com/compute/v1/projects/finance-team/zones/europe-west1-b/instances/scheduler-08",
    "service": "Compute Engine",
    "state": "ACTIVE",
    "status": "RUNNING",
    "tags": "project=app-project-035, env=uat",
    "zone": "europe-west1-b"
  },
  {
    "accountID": "marketing-team",
    "accountName": "marketing-team",
    "cpuAverage": 0.29,
    "cpuMaximum": 1,
    "cpuMinimum": 0.63,
    "hostname": null,
    "id": "4254929116841923950",
    "newResourceType": "Stop VM Instance",
    "platform": "Intel Cascade Lake",
    "primaryImpactCategory": "COST",
    "priority": "P3",
    "projectNumber": "107654322904",
    "recommendationDetails": "Save cost by stopping Idle VM 'data-scraper-06'.",
    "recommenderSubtype": "STOP_VM",
    "region": "us-central1",
    "resourceID": "4254929116841923950",
    "resourceName": "data-scraper-06",
    "resourceType": "n1-standard-8",
    "savings": 217.35,
    "savingsCurrency": "US$",
    "selfLink": "https://www.googleapis.com/compute/v1/projects/marketing-team/zones/us-central1-a/instances/data-scraper-06",
    "service": "Compute Engine",
    "state": "ACTIVE",
    "status": "RUNNING",
    "tags": "project=app-project-012, env=prod",
    "zone": "us-central1-a"
  },
  {
    "accountID": "devops-team",
    "accountName": "devops-team",
    "cpuAverage": 0.99,
    "cpuMaximum": 0.13,
    "cpuMinimum": 0.71,
    "hostname": null,
    "id": "3181249156841923950",
    "newResourceType": "Stop VM Instance",
    "platform": "Intel Skylake",
    "primaryImpactCategory": "COST",
    "priority": "P1",
    "projectNumber": "982321270904",
    "recommendationDetails": "Save cost by stopping Idle VM 'load-balancer-02'.",
    "recommenderSubtype": "STOP_VM",
    "region": "europe-west4",
    "resourceID": "3181249156841923950",
    "resourceName": "load-balancer-02",
    "resourceType": "n1-standard-2",
    "savings": 63.19,
    "savingsCurrency": "US$",
    "selfLink": "https://www.googleapis.com/compute/v1/projects/devops-team/zones/europe-west4-b/instances/load-balancer-02",
    "service": "Compute Engine",
    "state": "ACTIVE",
    "status": "RUNNING",
    "tags": "project=app-project-015, env=stg",
    "zone": "europe-west4-b"
  },
  {
    "accountID": "sales-team",
    "accountName": "sales-team",
    "cpuAverage": 0.41,
    "cpuMaximum": 0.97,
    "cpuMinimum": 0.79,
    "hostname": null,
    "id": "6719249116841923950",
    "newResourceType": "Stop VM Instance",
    "platform": "Intel Haswell",
    "primaryImpactCategory": "COST",
    "priority": "P2",
    "projectNumber": "645632890904",
    "recommendationDetails": "Save cost by stopping Idle VM 'api-gateway-05'.",
    "recommenderSubtype": "STOP_VM",
    "region": "us-west4",
    "resourceID": "6719249116841923950",
    "resourceName": "api-gateway-05",
    "resourceType": "n1-standard-6",
    "savings": 151.49,
    "savingsCurrency": "US$",
    "selfLink": "https://www.googleapis.com/compute/v1/projects/sales-team/zones/us-west4-a/instances/api-gateway-05",
    "service": "Compute Engine",
    "state": "ACTIVE",
    "status": "RUNNING",
    "tags": "project=app-project-027, env=poc",
    "zone": "us-west4-a"
  },
  {
    "accountID": "finance-team",
    "accountName": "finance-team",
    "cpuAverage": 0.55,
    "cpuMaximum": 0.79,
    "cpuMinimum": 0.35,
    "hostname": null,
    "id": "9156729116841923950",
    "newResourceType": "Stop VM Instance",
    "platform": "Intel Broadwell",
    "primaryImpactCategory": "COST",
    "priority": "P4",
    "projectNumber": "982321270904",
    "recommendationDetails": "Save cost by stopping Idle VM 'scheduler-08'.",
    "recommenderSubtype": "STOP_VM",
    "region": "europe-west1",
    "resourceID": "9156729116841923950",
    "resourceName": "scheduler-08",
    "resourceType": "n1-standard-4",
    "savings": 109.16,
    "savingsCurrency": "US$",
    "selfLink": "https://www.googleapis.com/compute/v1/projects/finance-team/zones/europe-west1-b/instances/scheduler-08",
    "service": "Compute Engine",
    "state": "ACTIVE",
    "status": "RUNNING",
    "tags": "project=app-project-035, env=uat",
    "zone": "europe-west1-b"
  }
]
